[
    {
        "codi": "Z1",
        "variables": [
            {
                "codi": 32,
                "lectures": [
                    {
                        "data": "2007-03-25T00:00Z",
                        "valor": -9.8,
                        "estat": "T",
                        "baseHoraria": "HO"
                    },
                    {
                        "data": "2007-03-25T01:00Z",
                        "valor": -9.7,
                        "estat": "T",
                        "baseHoraria": "HO"
                    },
                    {
                        "data": "2007-03-25T02:00Z",
                        "valor": -9.2,
                        "estat": "T",
                        "baseHoraria": "HO"
                    },
                    {
                        "data": "2007-03-25T03:00Z",
                        "valor": -9.1,
                        "estat": "T",
                        "baseHoraria": "HO"
                    },
                    {
                        "data": "2007-03-25T04:00Z",
                        "valor": -9.0,
                        "estat": "T",
                        "baseHoraria": "HO"
                    },
                    {
                        "data": "2007-03-25T05:00Z",
                        "valor": -9.0,
                        "estat": "T",
                        "baseHoraria": "HO"
                    },
                    {
                        "data": "2007-03-25T06:00Z",
                        "valor": -8.9,
                        "estat": "T",
                        "baseHoraria": "HO"
                    },
                    {
                        "data": "2007-03-25T07:00Z",
                        "valor": -8.3,
                        "estat": "T",
                        "baseHoraria": "HO"
                    },
                    {
                        "data": "2007-03-25T08:00Z",
                        "valor": -6.2,
                        "estat": "T",
                        "baseHoraria": "HO"
                    },
                    {
                        "data": "2007-03-25T09:00Z",
                        "valor": -3.7,
                        "estat": "T",
                        "baseHoraria": "HO"
                    },
                    {
                        "data": "2007-03-25T10:00Z",
                        "valor": -2.7,
                        "estat": "T",
                        "baseHoraria": "HO"
                    },
                    {
                        "data": "2007-03-25T11:00Z",
                        "valor": -0.7,
                        "estat": "T",
                        "baseHoraria": "HO"
                    },
                    {
                        "data": "2007-03-25T12:00Z",
                        "valor": -0.2,
                        "estat": "T",
                        "baseHoraria": "HO"
                    },
                    {
                        "data": "2007-03-25T13:00Z",
                        "valor": -0.1,
                        "estat": "T",
                        "baseHoraria": "HO"
                    },
                    {
                        "data": "2007-03-25T14:00Z",
                        "valor": -0.1,
                        "estat": "T",
                        "baseHoraria": "HO"
                    },
                    {
                        "data": "2007-03-25T15:00Z",
                        "valor": -0.1,
                        "estat": "T",
                        "baseHoraria": "HO"
                    },
                    {
                        "data": "2007-03-25T16:00Z",
                        "valor": -0.4,
                        "estat": "T",
                        "baseHoraria": "HO"
                    },
                    {
                        "data": "2007-03-25T17:00Z",
                        "valor": -4.7,
                        "estat": "T",
                        "baseHoraria": "HO"
                    },
                    {
                        "data": "2007-03-25T18:00Z",
                        "valor": -5.9,
                        "estat": "T",
                        "baseHoraria": "HO"
                    },
                    {
                        "data": "2007-03-25T19:00Z",
                        "valor": -6.0,
                        "estat": "T",
                        "baseHoraria": "HO"
                    },
                    {
                        "data": "2007-03-25T20:00Z",
                        "valor": -6.8,
                        "estat": "T",
                        "baseHoraria": "HO"
                    },
                    {
                        "data": "2007-03-25T21:00Z",
                        "valor": -6.2,
                        "estat": "T",
                        "baseHoraria": "HO"
                    },
                    {
                        "data": "2007-03-25T22:00Z",
                        "valor": -6.1,
                        "estat": "T",
                        "baseHoraria": "HO"
                    },
                    {
                        "data": "2007-03-25T23:00Z",
                        "valor": -6.2,
                        "estat": "T",
                        "baseHoraria": "HO"
                    }
                ]
            }
        ]
    }
]